RsAts1800c/RsAts1800c.py
RsAts1800c/__init__.py
RsAts1800c/enums.py
RsAts1800c/Implementations/Utilities.py
RsAts1800c/Implementations/__init__.py
RsAts1800c/Implementations/Azimuth/StepMovement.py
RsAts1800c/Implementations/Azimuth/TriggerOutput.py
RsAts1800c/Implementations/Azimuth/__init__.py
RsAts1800c/Implementations/Elevation/StepMovement.py
RsAts1800c/Implementations/Elevation/TriggerOutput.py
RsAts1800c/Implementations/Elevation/__init__.py
RsAts1800c/Implementations/FeedSwitcher/__init__.py
RsAts1800c/Implementations/System/__init__.py
RsAts1800c/Internal/Conversions.py
RsAts1800c/Internal/Instrument.py
RsAts1800c/Internal/InstrumentErrors.py
RsAts1800c/Internal/Utilities.py
RsAts1800c/Internal/__init__.py
RsAts1800c-1.2.0.3.dist-info/METADATA
RsAts1800c-1.2.0.3.dist-info/WHEEL
RsAts1800c-1.2.0.3.dist-info/top_level.txt
RsAts1800c-1.2.0.3.dist-info/RECORD
