Metadata-Version: 2.1
Name: RsAts1800c
Version: 1.2.0.3
Summary: ATS1800C Python instrument driver from Rohde & Schwarz
Home-page: UNKNOWN
Author: Rohde & Schwarz GmbH & Co. KG
Author-email: Customer.Support@rohde-schwarz.com
License: MIT
Platform: UNKNOWN
Classifier: License :: OSI Approved :: MIT License
Classifier: Programming Language :: Python :: 3.7
Requires-Dist: PyVisa (>=1.11.3)
